qml_element/__init__.py
qml_element/rc_qml_element.py
qml_element-1.0.1.data/data/Lib/site-packages/qml_element/componentLib/DatePicker.qml
qml_element-1.0.1.data/data/Lib/site-packages/qml_element/componentLib/ElMonthGrid.qml
qml_element-1.0.1.data/data/Lib/site-packages/qml_element/componentLib/FlatButton.qml
qml_element-1.0.1.data/data/Lib/site-packages/qml_element/componentLib/Link.qml
qml_element-1.0.1.data/data/Lib/site-packages/qml_element/componentLib/ShadowRectangle.qml
qml_element-1.0.1.data/data/Lib/site-packages/qml_element/componentLib/componentLib.dll
qml_element-1.0.1.data/data/Lib/site-packages/qml_element/componentLib/componentLib.qmltypes
qml_element-1.0.1.data/data/Lib/site-packages/qml_element/componentLib/componentLibplugin.dll
qml_element-1.0.1.data/data/Lib/site-packages/qml_element/componentLib/libcomponentLib.a
qml_element-1.0.1.data/data/Lib/site-packages/qml_element/componentLib/qmldir
qml_element-1.0.1.dist-info/LICENSE
qml_element-1.0.1.dist-info/METADATA
qml_element-1.0.1.dist-info/WHEEL
qml_element-1.0.1.dist-info/top_level.txt
qml_element-1.0.1.dist-info/RECORD
