Metadata-Version: 2.1
Name: qml-element
Version: 1.0.1
Summary: 仿element ui样式风格的qml组件库
Home-page: UNKNOWN
Author: 林柏君
Author-email: 1355767057@qq.com
License: UNKNOWN
Platform: UNKNOWN
License-File: LICENSE
